gt1000pilot/__init__.py
gt1000pilot/app.py
gt1000pilot/assets/resize.js
gt1000pilot/assets/stompbox-comp.png
gt1000pilot/assets/stompbox-dist.png
gt1000pilot/assets/stompbox-eq.png
gt1000pilot/assets/stompbox-fx.png
gt1000pilot/callbacks.py
gt1000pilot/dump.py
gt1000pilot/pages/chorus.py
gt1000pilot/pages/comp.py
gt1000pilot/pages/delay.py
gt1000pilot/pages/dist.py
gt1000pilot/pages/eq.py
gt1000pilot/pages/fx.py
gt1000pilot/pages/mstDelay.py
gt1000pilot/pages/ns.py
gt1000pilot/pages/pages_common.py
gt1000pilot/pages/pedalFx.py
gt1000pilot/pages/preamp.py
gt1000pilot/pages/reverb.py
gt1000pilot/shared.py
gt_1000pilot-0.2.0.dist-info/LICENSE
gt_1000pilot-0.2.0.dist-info/METADATA
gt_1000pilot-0.2.0.dist-info/WHEEL
gt_1000pilot-0.2.0.dist-info/RECORD
