Metadata-Version: 2.1
Name: GT-1000PILOT
Version: 0.2.0
Summary: 
Home-page: https://github.com/jdesfossez/GT-1000PILOT
License: GPLv2
Author: Julien Desfossez
Author-email: j@jdfz.org
Requires-Python: >=3.10,<4.0
Classifier: License :: Other/Proprietary License
Classifier: Programming Language :: Python :: 3
Classifier: Programming Language :: Python :: 3.10
Classifier: Programming Language :: Python :: 3.11
Classifier: Programming Language :: Python :: 3.12
Requires-Dist: dash (>=2.17.1,<3.0.0)
Requires-Dist: dash-bootstrap-components (>=1.6.0,<2.0.0)
Requires-Dist: pygt1000 (>=0.1.5,<0.2.0)
Requires-Dist: python-rtmidi (>=1.5.8,<2.0.0)
Project-URL: Repository, https://github.com/jdesfossez/GT-1000PILOT
